snakes_on_a_plane-0.1.0.dist-info/DESCRIPTION.rst
snakes_on_a_plane-0.1.0.dist-info/entry_points.txt
snakes_on_a_plane-0.1.0.dist-info/METADATA
snakes_on_a_plane-0.1.0.dist-info/metadata.json
snakes_on_a_plane-0.1.0.dist-info/RECORD
snakes_on_a_plane-0.1.0.dist-info/top_level.txt
snakes_on_a_plane-0.1.0.dist-info/WHEEL
xplane/__init__.py
xplane/autopilot.py
xplane/io.py
xplane/packets.py
