Metadata-Version: 2.0
Name: snakes-on-a-plane
Version: 0.1.0
Summary: A set of tools for interfacing with X-Plane 10.
Home-page: https://github.com/tomleese/pyxplane
Author: Tom Leese
Author-email: inbox@tomleese.me.uk
License: UNKNOWN
Platform: UNKNOWN
Classifier: Development Status :: 3 - Alpha
Classifier: License :: OSI Approved :: MIT License
Classifier: Programming Language :: Python :: 3
Classifier: Programming Language :: Python :: 3.3
Classifier: Programming Language :: Python :: 3.4
Requires-Dist: Pint
